{
  "sessions": [
    {
      "token": "admin-1773307705395-hmp81u6yf5o",
      "expiresAt": "2026-03-13T09:28:25.395Z",
      "userId": "super"
    },
    {
      "token": "admin-1773307935159-yzzvwrl6zoq",
      "expiresAt": "2026-03-13T09:32:15.159Z",
      "userId": "super"
    },
    {
      "token": "admin-1773332790654-kzvpsjslstf",
      "expiresAt": "2026-03-13T16:26:30.654Z",
      "userId": "super"
    },
    {
      "token": "admin-1773333023524-h87fg00f3e",
      "expiresAt": "2026-03-13T16:30:23.524Z",
      "userId": "super"
    },
    {
      "token": "admin-1773368215206-29j7s317rwx",
      "expiresAt": "2026-03-14T02:16:55.206Z",
      "userId": "techteam"
    },
    {
      "token": "admin-1773368787473-iqff0ni8rhf",
      "expiresAt": "2026-03-14T02:26:27.473Z",
      "userId": "techteam"
    },
    {
      "token": "admin-1773371782782-b1kppvndtq6",
      "expiresAt": "2026-03-14T03:16:22.782Z",
      "userId": "techteam"
    },
    {
      "token": "admin-1773373011122-rgu70qq5w6",
      "expiresAt": "2026-03-14T03:36:51.122Z",
      "userId": "super"
    },
    {
      "token": "admin-1773373838856-12j513zdl0ma",
      "expiresAt": "2026-03-14T03:50:38.856Z",
      "userId": "super"
    },
    {
      "token": "admin-1773378037676-ov7klv8xkb",
      "expiresAt": "2026-03-14T05:00:37.676Z",
      "userId": "techteam"
    },
    {
      "token": "admin-1773378190697-4w4gi9t207g",
      "expiresAt": "2026-03-14T05:03:10.697Z",
      "userId": "techteam"
    },
    {
      "token": "admin-1773378485351-jfppesd2zs",
      "expiresAt": "2026-03-14T05:08:05.351Z",
      "userId": "techteam"
    },
    {
      "token": "admin-1773378711483-qze9la5bb7f",
      "expiresAt": "2026-03-14T05:11:51.483Z",
      "userId": "super"
    },
    {
      "token": "admin-1773378966121-0ok63c6w236",
      "expiresAt": "2026-03-14T05:16:06.121Z",
      "userId": "super"
    },
    {
      "token": "admin-1773379001387-pvlo77pre9",
      "expiresAt": "2026-03-14T05:16:41.387Z",
      "userId": "super"
    },
    {
      "token": "admin-1773379265693-k815kcy7qrr",
      "expiresAt": "2026-03-14T05:21:05.693Z",
      "userId": "techteam"
    },
    {
      "token": "admin-1773379284665-dr3jg8pytsk",
      "expiresAt": "2026-03-14T05:21:24.665Z",
      "userId": "super"
    },
    {
      "token": "admin-1773379299679-4lmd96cozg",
      "expiresAt": "2026-03-14T05:21:39.679Z",
      "userId": "techteam"
    },
    {
      "token": "admin-1773379320844-lyd6h1pjpsf",
      "expiresAt": "2026-03-14T05:22:00.844Z",
      "userId": "techteam"
    },
    {
      "token": "admin-1773379390462-klnkc127v59",
      "expiresAt": "2026-03-14T05:23:10.462Z",
      "userId": "techteam"
    },
    {
      "token": "admin-1773379663364-6hueucaave8",
      "expiresAt": "2026-03-14T05:27:43.364Z",
      "userId": "super"
    },
    {
      "token": "admin-1773379796104-edzlxh2xgz9",
      "expiresAt": "2026-03-14T05:29:56.104Z",
      "userId": "super"
    },
    {
      "token": "admin-1773379966388-fat6d3on8bu",
      "expiresAt": "2026-03-14T05:32:46.388Z",
      "userId": "super"
    },
    {
      "token": "admin-1773380220987-2xgnzch6j7w",
      "expiresAt": "2026-03-14T05:37:00.987Z",
      "userId": "super"
    },
    {
      "token": "admin-1773380649397-zhqw80mdh4f",
      "expiresAt": "2026-03-14T05:44:09.397Z",
      "userId": "super"
    },
    {
      "token": "admin-1773380898598-3d1bq0aoxu7",
      "expiresAt": "2026-03-14T05:48:18.598Z",
      "userId": "super"
    },
    {
      "token": "admin-1773380941463-31y3iewedq",
      "expiresAt": "2026-03-14T05:49:01.463Z",
      "userId": "super"
    },
    {
      "token": "admin-1773381085693-3unchi43wnk",
      "expiresAt": "2026-03-14T05:51:25.693Z",
      "userId": "super"
    },
    {
      "token": "admin-1773382518311-jnoer8nu7r",
      "expiresAt": "2026-03-14T06:15:18.311Z",
      "userId": "super"
    },
    {
      "token": "admin-1773383977535-ksi9hh8oi3g",
      "expiresAt": "2026-03-14T06:39:37.535Z",
      "userId": "techteam"
    },
    {
      "token": "admin-1773384823355-6ujalm206f6",
      "expiresAt": "2026-03-14T06:53:43.355Z",
      "userId": "techteam"
    },
    {
      "token": "admin-1773384903329-dae7oile2xm",
      "expiresAt": "2026-03-14T06:55:03.329Z",
      "userId": "techteam"
    },
    {
      "token": "admin-1773385165581-bm5xag1zfgk",
      "expiresAt": "2026-03-14T06:59:25.581Z",
      "userId": "techteam"
    },
    {
      "token": "admin-1773385322655-krka24fr9q",
      "expiresAt": "2026-03-14T07:02:02.655Z",
      "userId": "techteam"
    },
    {
      "token": "admin-1773385387578-8ssvh7vu9qg",
      "expiresAt": "2026-03-14T07:03:07.578Z",
      "userId": "techteam"
    },
    {
      "token": "admin-1773385527657-ykjenb9hycp",
      "expiresAt": "2026-03-14T07:05:27.657Z",
      "userId": "super"
    },
    {
      "token": "admin-1773386053192-3wpdmvfpmry",
      "expiresAt": "2026-03-14T07:14:13.192Z",
      "userId": "techteam"
    },
    {
      "token": "admin-1773386930000-h2e7soggmac",
      "expiresAt": "2026-03-14T07:28:50.000Z",
      "userId": "super"
    },
    {
      "token": "admin-1773387278896-hj7bvdwr5d",
      "expiresAt": "2026-03-14T07:34:38.896Z",
      "userId": "techteam"
    },
    {
      "token": "admin-1773388375941-b838xes8dnf",
      "expiresAt": "2026-03-14T07:52:55.941Z",
      "userId": "techteam"
    },
    {
      "token": "admin-1773388399915-larabirwcof",
      "expiresAt": "2026-03-14T07:53:19.915Z",
      "userId": "techteam"
    },
    {
      "token": "admin-1773388965999-kk1ilk2yac",
      "expiresAt": "2026-03-14T08:02:45.999Z",
      "userId": "techteam"
    },
    {
      "token": "admin-1773389318946-m4de7589w7",
      "expiresAt": "2026-03-14T08:08:38.946Z",
      "userId": "techteam"
    },
    {
      "token": "admin-1773389406109-6hgrotxsmnc",
      "expiresAt": "2026-03-14T08:10:06.109Z",
      "userId": "techteam"
    },
    {
      "token": "admin-1773389711176-sehfafj4rdc",
      "expiresAt": "2026-03-14T08:15:11.176Z",
      "userId": "techteam"
    },
    {
      "token": "admin-1773389886182-gr2h1ajcstk",
      "expiresAt": "2026-03-14T08:18:06.182Z",
      "userId": "techteam"
    },
    {
      "token": "admin-1773391375997-71n42demgh4",
      "expiresAt": "2026-03-14T08:42:55.997Z",
      "userId": "techteam"
    }
  ]
}